{
  "points": {
    "1": {
      "$type": "DungeonExit",
      "MKHHFMFNPHG": {
        "x": 5,
        "y": 5,
        "z": 5
      },
      "BIELLMDIODE": "",
      "HDMEDFBJMPK": 0,
      "tranRot": {
        "x": 0,
        "y": 0,
        "z": 0
      },
      "pos": {
        "x": 499.268,
        "y": 250.01385,
        "z": 1482.2612
      },
      "CEONPLGFMNI": 0,
      "EICLDEIJGGB": false,
      "MPPBCFKHGHA": false,
      "NIGJGLDEKAD": false,
      "POGLHNAHJNK": false,
      "areaId": 0,
      "tranPos": {
        "x": 500.6022,
        "y": 250.0139,
        "z": 1511.885
      },
      "MEGMIMEDODJ": "NORMAL",
      "gadgetId": 70120004,
      "rot": {
        "x": 0,
        "y": 0,
        "z": 0
      }
    }
  }
}